{
  "version": "1.0",
  "defaultProvider": "unpkg",
  "libraries": [
    {
      "library": "@microsoft/signalr@latest",
      "destination": "wwwroot/js/signalr/",
      "files": [
        "dist/browser/signalr.js",
        "dist/browser/signalr.min.js"
      ]
    },
    {
      "provider": "cdnjs",
      "library": "chosen@1.8.7",
      "destination": "wwwroot/lib/chosen/"
    },
    {
      "provider": "cdnjs",
      "library": "select2@4.0.13",
      "destination": "wwwroot/lib/select2/"
    }
  ]
}